pybuilder_smart_copy_resources/__init__.py
pybuilder_smart_copy_resources-0.1.6.dist-info/DESCRIPTION.rst
pybuilder_smart_copy_resources-0.1.6.dist-info/METADATA
pybuilder_smart_copy_resources-0.1.6.dist-info/RECORD
pybuilder_smart_copy_resources-0.1.6.dist-info/WHEEL
pybuilder_smart_copy_resources-0.1.6.dist-info/metadata.json
pybuilder_smart_copy_resources-0.1.6.dist-info/namespace_packages.txt
pybuilder_smart_copy_resources-0.1.6.dist-info/top_level.txt
pybuilder_smart_copy_resources-0.1.6.dist-info/zip-safe
