Metadata-Version: 2.0
Name: pybuilder-smart-copy-resources
Version: 0.1.6
Summary: PyBuilder plugin for copying additional resources
Home-page: https://github.com/margru/pybuilder-smart-copy-resources
Author: Martin Gruber
Author-email: martin.gruber@email.cz
License: MIT
Platform: UNKNOWN
Classifier: Development Status :: 3 - Alpha
Classifier: License :: OSI Approved :: MIT License
Classifier: Programming Language :: Python :: 2.7
